<?xml version="1.0" encoding="UTF-8"?>
<!DOCTYPE mapper PUBLIC "-//mybatis.org//DTD Mapper 3.0//EN" "http://mybatis.org/dtd/mybatis-3-mapper.dtd">

<mapper namespace="com.keith.modules.dao.template.ProFeightTemplateDao">

	<!-- 可根据自己的需求，是否要使用 -->
    <resultMap type="com.keith.modules.entity.template.ProFeightTemplate" id="proFeightTemplateMap">
        <result property="id" column="id"/>
        <result property="userAdminId" column="user_admin_id"/>
        <result property="productId" column="product_id"/>
        <result property="chargeType" column="charge_type"/>
        <result property="name" column="name"/>
        <result property="defaultStatus" column="default_status"/>
        <result property="temTypt" column="tem_typt"/>
        <result property="createTime" column="create_time"/>
    </resultMap>


</mapper>